textlangid/__init__.py
textlangid/textlangid.py
textlangid-0.0.7.dist-info/METADATA
textlangid-0.0.7.dist-info/WHEEL
textlangid-0.0.7.dist-info/top_level.txt
textlangid-0.0.7.dist-info/RECORD
