Metadata-Version: 2.1
Name: textlangid
Version: 0.0.7
Summary: Detects the language of text
Home-page: https://github.com/tools4eu/text-language-identifier
Author: tools4eu
Author-email: openeuro@proton.me
Project-URL: Bug Tracker, https://github.com/tools4eu/text-language-identifier/issues
Classifier: Programming Language :: Python :: 3
Classifier: License :: OSI Approved :: MIT License
Classifier: Operating System :: OS Independent
Requires-Python: >=3.6
Requires-Dist: fasttext-wheel
Requires-Dist: huggingface-hub
Requires-Dist: processors
Requires-Dist: numpy <2.0.0
